zeon/__init__.py
zeon/files.py
zeon/main.py
zeon-1.0.1.dist-info/METADATA
zeon-1.0.1.dist-info/WHEEL
zeon-1.0.1.dist-info/entry_points.txt
zeon-1.0.1.dist-info/top_level.txt
zeon-1.0.1.dist-info/RECORD
