Metadata-Version: 2.4
Name: zeon
Version: 1.0.1
Summary: A powerful CLI tool to scaffold and manage FastAPI projects with authentication, database migrations, and more
Author-email: Vinyas Bharadwaj <vinyasbharadwaj101@gmail.com>
License-Expression: MIT
Project-URL: Homepage, https://github.com/vinyasbharadwaj/zeon
Project-URL: Repository, https://github.com/vinyasbharadwaj/zeon
Project-URL: Documentation, https://github.com/vinyasbharadwaj/zeon#readme
Project-URL: Bug Tracker, https://github.com/vinyasbharadwaj/zeon/issues
Keywords: fastapi,cli,scaffolding,web,api,authentication,jwt,sqlalchemy,alembic
Classifier: Development Status :: 4 - Beta
Classifier: Intended Audience :: Developers
Classifier: Programming Language :: Python :: 3
Classifier: Programming Language :: Python :: 3.8
Classifier: Programming Language :: Python :: 3.9
Classifier: Programming Language :: Python :: 3.10
Classifier: Programming Language :: Python :: 3.11
Classifier: Programming Language :: Python :: 3.12
Classifier: Framework :: FastAPI
Classifier: Topic :: Software Development :: Code Generators
Classifier: Topic :: Software Development :: Libraries :: Application Frameworks
Classifier: Topic :: Internet :: WWW/HTTP :: HTTP Servers
Requires-Python: >=3.8
Requires-Dist: typer>=0.9.0
Requires-Dist: fastapi>=0.100.0
Requires-Dist: uvicorn[standard]>=0.20.0
Requires-Dist: sqlalchemy>=2.0.0
Requires-Dist: passlib[bcrypt]>=1.7.4
Requires-Dist: python-jose[cryptography]>=3.3.0
Requires-Dist: python-multipart>=0.0.6
Requires-Dist: python-dotenv>=1.0.0
Requires-Dist: pydantic[email]>=2.0.0
Requires-Dist: alembic>=1.12.0
Provides-Extra: dev
Requires-Dist: pytest>=7.0.0; extra == "dev"
Requires-Dist: pytest-asyncio>=0.21.0; extra == "dev"
Requires-Dist: httpx>=0.24.0; extra == "dev"
